termibase/__init__.py
termibase/__main__.py
termibase/cli/__init__.py
termibase/cli/input_handler.py
termibase/cli/main.py
termibase/demos/__init__.py
termibase/demos/data.py
termibase/engine/__init__.py
termibase/engine/simulator.py
termibase/learn/__init__.py
termibase/learn/content.py
termibase/learn/lesson.py
termibase/learn/menu.py
termibase/parser/__init__.py
termibase/parser/analyzer.py
termibase/storage/__init__.py
termibase/storage/engine.py
termibase/tests/__init__.py
termibase/tests/test_analyzer.py
termibase/tests/test_storage.py
termibase/visualizer/__init__.py
termibase/visualizer/renderer.py
termibase-0.1.7.dist-info/licenses/LICENSE
termibase_setup/__init__.py
termibase_setup/__main__.py
termibase-0.1.7.dist-info/METADATA
termibase-0.1.7.dist-info/WHEEL
termibase-0.1.7.dist-info/entry_points.txt
termibase-0.1.7.dist-info/top_level.txt
termibase-0.1.7.dist-info/RECORD
