Metadata-Version: 2.4
Name: termibase
Version: 0.1.7
Summary: A terminal-native database learning playground
Home-page: https://github.com/yourusername/termibase
Author: TermiBase Contributors
Author-email: Tej Gokani <tejmgokani@gmail.com>
License: Source-Available License (TSAL)
Project-URL: Homepage, https://github.com/tejgokani/TermiBase
Project-URL: Repository, https://github.com/tejgokani/TermiBase
Project-URL: Issues, https://github.com/tejgokani/TermiBase/issues
Keywords: database,sql,education,cli,terminal
Classifier: Development Status :: 3 - Alpha
Classifier: Intended Audience :: Education
Classifier: Intended Audience :: Developers
Classifier: License :: Other/Proprietary License
Classifier: Programming Language :: Python :: 3
Classifier: Programming Language :: Python :: 3.8
Classifier: Programming Language :: Python :: 3.9
Classifier: Programming Language :: Python :: 3.10
Classifier: Programming Language :: Python :: 3.11
Classifier: Operating System :: OS Independent
Requires-Python: >=3.8
License-File: LICENSE
Requires-Dist: typer>=0.9.0
Requires-Dist: rich>=13.0.0
Requires-Dist: sqlparse>=0.4.4
Dynamic: author
Dynamic: home-page
Dynamic: license-file
Dynamic: requires-python
